{
  "project_info": {
    "project_number": "361561969204",
    "project_id": "login-6a3e2",
    "storage_bucket": "login-6a3e2.appspot.com"
  },
  "client": [
    {
      "client_info": {
        "mobilesdk_app_id": "1:361561969204:android:5b575c131ba7b5abd07061",
        "android_client_info": {
          "package_name": "com.srf786"
        }
      },
      "oauth_client": [
        {
          "client_id": "361561969204-mjeuem7vr5t83g0n772giav2u4r3l52l.apps.googleusercontent.com",
          "client_type": 3
        }
      ],
      "api_key": [
        {
          "current_key": "AIzaSyAfvvEsYBqn-jIkgLZWyR2Z33fEUYKCIUo"
        }
      ],
      "services": {
        "appinvite_service": {
          "other_platform_oauth_client": [
            {
              "client_id": "361561969204-mjeuem7vr5t83g0n772giav2u4r3l52l.apps.googleusercontent.com",
              "client_type": 3
            }
          ]
        }
      }
    }
  ],
  "configuration_version": "1"
}